bfasta/FastAreader.py
bfasta/__init__.py
bfasta-0.1.1.dist-info/LICENSE
bfasta-0.1.1.dist-info/METADATA
bfasta-0.1.1.dist-info/WHEEL
bfasta-0.1.1.dist-info/RECORD
