Metadata-Version: 2.1
Name: bfasta
Version: 0.1.1
Summary: Simple fasta reader with no dependencies
Home-page: https://github.com/retospect/bfasta
License: GPL-3
Keywords: fasta,genomics,bioinformatics,bio
Author: Reto Stamm
Classifier: License :: Other/Proprietary License
Classifier: Programming Language :: Python
Classifier: Programming Language :: Python :: 2
Classifier: Programming Language :: Python :: 2.7
Classifier: Programming Language :: Python :: 3
Classifier: Programming Language :: Python :: 3.4
Classifier: Programming Language :: Python :: 3.5
Classifier: Programming Language :: Python :: 3.6
Classifier: Programming Language :: Python :: 3.7
Classifier: Programming Language :: Python :: 3.8
Classifier: Programming Language :: Python :: 3.9
Classifier: Programming Language :: Python :: 3.10
Classifier: Programming Language :: Python :: 3.11
